LICENSE
MANIFEST.in
README.rst
setup.py
corto/__init__.py
corto/corto.py
corto.egg-info/PKG-INFO
corto.egg-info/SOURCES.txt
corto.egg-info/dependency_links.txt
corto.egg-info/top_level.txt
test/test_corto.py